mc_enchanter/__init__.py
mc_enchanter/enchantable.py
mc_enchanter/enchantment.py
mc_enchanter/mc_enchanter.py
mc_enchanter/utils.py
mc_enchanter-0.0.5.dist-info/LICENCE
mc_enchanter-0.0.5.dist-info/METADATA
mc_enchanter-0.0.5.dist-info/WHEEL
mc_enchanter-0.0.5.dist-info/top_level.txt
mc_enchanter-0.0.5.dist-info/RECORD
