Metadata-Version: 2.1
Name: mc-enchanter
Version: 0.0.5
Summary: A small python module that masters Minecraft enchanting mechanics.
Home-page: https://github.com/GZPERRA/MC-Enchanter
Author: GZPERRA
License: UNKNOWN
Platform: UNKNOWN
Classifier: Programming Language :: Python :: 3
Classifier: Operating System :: OS Independent
Requires-Python: >=3.6
